ezpath.py
ezpath-1.7.dist-info/METADATA
ezpath-1.7.dist-info/WHEEL
ezpath-1.7.dist-info/top_level.txt
ezpath-1.7.dist-info/RECORD
