Metadata-Version: 2.4
Name: ezpath
Version: 1.7
Summary: Turn-Key solution to manage paths relative to the current file
Author: Vittorio Pascucci
Requires-Python: >=3.6
Dynamic: author
Dynamic: description
Dynamic: description-content-type
Dynamic: requires-python
Dynamic: summary
